Workbook

Sheet Students
A1: Student Grade Analysis
A3: StudentID | B3: Full Name | C3: Math | D3: Science | E3: Total | F3: Average | G3: Grade | H3: Above80_Both (AND) | I3: First Name (TEXT) | J3: Name (UPPER)
A4: S101 | B4: Aarav Sharma | C4: 92 | D4: 85 | E4: =C4+D4 -> 177 | F4: =E4/2 -> 88.5 | G4: =IF(F4>=90,"A",IF(F4>=75,"B",IF(F4>=60,"C",IF(F4>=40,"D","F")))) -> B | H4: =IF(AND(C4>80,D4>80),"Yes","No") -> Yes | I4: =LEFT(B4,FIND(" ",B4)-1) -> Aarav | J4: =UPPER(B4) -> AARAV SHARMA
A5: S102 | B5: Diya Patel | C5: 55 | D5: 60 | E5: =C5+D5 -> 115 | F5: =E5/2 -> 57.5 | G5: =IF(F5>=90,"A",IF(F5>=75,"B",IF(F5>=60,"C",IF(F5>=40,"D","F")))) -> D | H5: =IF(AND(C5>80,D5>80),"Yes","No") -> No | I5: =LEFT(B5,FIND(" ",B5)-1) -> Diya | J5: =UPPER(B5) -> DIYA PATEL
A6: S103 | B6: Vivaan Gupta | C6: 78 | D6: 82 | E6: =C6+D6 -> 160 | F6: =E6/2 -> 80 | G6: =IF(F6>=90,"A",IF(F6>=75,"B",IF(F6>=60,"C",IF(F6>=40,"D","F")))) -> B | H6: =IF(AND(C6>80,D6>80),"Yes","No") -> No | I6: =LEFT(B6,FIND(" ",B6)-1) -> Vivaan | J6: =UPPER(B6) -> VIVAAN GUPTA
A7: S104 | B7: Isha Verma | C7: 88 | D7: 91 | E7: =C7+D7 -> 179 | F7: =E7/2 -> 89.5 | G7: =IF(F7>=90,"A",IF(F7>=75,"B",IF(F7>=60,"C",IF(F7>=40,"D","F")))) -> B | H7: =IF(AND(C7>80,D7>80),"Yes","No") -> Yes | I7: =LEFT(B7,FIND(" ",B7)-1) -> Isha | J7: =UPPER(B7) -> ISHA VERMA
A8: S105 | B8: Kabir Singh | C8: 45 | D8: 50 | E8: =C8+D8 -> 95 | F8: =E8/2 -> 47.5 | G8: =IF(F8>=90,"A",IF(F8>=75,"B",IF(F8>=60,"C",IF(F8>=40,"D","F")))) -> D | H8: =IF(AND(C8>80,D8>80),"Yes","No") -> No | I8: =LEFT(B8,FIND(" ",B8)-1) -> Kabir | J8: =UPPER(B8) -> KABIR SINGH
A9: S106 | B9: Anaya Joshi | C9: 95 | D9: 89 | E9: =C9+D9 -> 184 | F9: =E9/2 -> 92 | G9: =IF(F9>=90,"A",IF(F9>=75,"B",IF(F9>=60,"C",IF(F9>=40,"D","F")))) -> A | H9: =IF(AND(C9>80,D9>80),"Yes","No") -> Yes | I9: =LEFT(B9,FIND(" ",B9)-1) -> Anaya | J9: =UPPER(B9) -> ANAYA JOSHI
A10: S107 | B10: Reyansh Mehta | C10: 62 | D10: 58 | E10: =C10+D10 -> 120 | F10: =E10/2 -> 60 | G10: =IF(F10>=90,"A",IF(F10>=75,"B",IF(F10>=60,"C",IF(F10>=40,"D","F")))) -> C | H10: =IF(AND(C10>80,D10>80),"Yes","No") -> No | I10: =LEFT(B10,FIND(" ",B10)-1) -> Reyansh | J10: =UPPER(B10) -> REYANSH MEHTA
A11: S108 | B11: Myra Nair | C11: 33 | D11: 40 | E11: =C11+D11 -> 73 | F11: =E11/2 -> 36.5 | G11: =IF(F11>=90,"A",IF(F11>=75,"B",IF(F11>=60,"C",IF(F11>=40,"D","F")))) -> F | H11: =IF(AND(C11>80,D11>80),"Yes","No") -> No | I11: =LEFT(B11,FIND(" ",B11)-1) -> Myra | J11: =UPPER(B11) -> MYRA NAIR
A12: S109 | B12: Aditya Rao | C12: 81 | D12: 84 | E12: =C12+D12 -> 165 | F12: =E12/2 -> 82.5 | G12: =IF(F12>=90,"A",IF(F12>=75,"B",IF(F12>=60,"C",IF(F12>=40,"D","F")))) -> B | H12: =IF(AND(C12>80,D12>80),"Yes","No") -> Yes | I12: =LEFT(B12,FIND(" ",B12)-1) -> Aditya | J12: =UPPER(B12) -> ADITYA RAO
A13: S110 | B13: Saanvi Iyer | C13: 70 | D13: 75 | E13: =C13+D13 -> 145 | F13: =E13/2 -> 72.5 | G13: =IF(F13>=90,"A",IF(F13>=75,"B",IF(F13>=60,"C",IF(F13>=40,"D","F")))) -> C | H13: =IF(AND(C13>80,D13>80),"Yes","No") -> No | I13: =LEFT(B13,FIND(" ",B13)-1) -> Saanvi | J13: =UPPER(B13) -> SAANVI IYER
A14: S111 | B14: Arjun Kapoor | C14: 58 | D14: 65 | E14: =C14+D14 -> 123 | F14: =E14/2 -> 61.5 | G14: =IF(F14>=90,"A",IF(F14>=75,"B",IF(F14>=60,"C",IF(F14>=40,"D","F")))) -> C | H14: =IF(AND(C14>80,D14>80),"Yes","No") -> No | I14: =LEFT(B14,FIND(" ",B14)-1) -> Arjun | J14: =UPPER(B14) -> ARJUN KAPOOR
A15: S112 | B15: Ira Malhotra | C15: 90 | D15: 93 | E15: =C15+D15 -> 183 | F15: =E15/2 -> 91.5 | G15: =IF(F15>=90,"A",IF(F15>=75,"B",IF(F15>=60,"C",IF(F15>=40,"D","F")))) -> A | H15: =IF(AND(C15>80,D15>80),"Yes","No") -> Yes | I15: =LEFT(B15,FIND(" ",B15)-1) -> Ira | J15: =UPPER(B15) -> IRA MALHOTRA
... A18: S115 | B18: Shaurya Reddy | C18: 66 | D18: 72 | E18: =C18+D18 -> 138 | F18: =E18/2 -> 69 | G18: =IF(F18>=90,"A",IF(F18>=75,"B",IF(F18>=60,"C",IF(F18>=40,"D","F")))) -> C | H18: =IF(AND(C18>80,D18>80),"Yes","No") -> No | I18: =LEFT(B18,FIND(" ",B18)-1) -> Shaurya | J18: =UPPER(B18) -> SHAURYA REDDY
A21: Analysis / Formula Demos
A22: Students scoring above 60 in Math (COUNTIFS): | C22: =COUNTIFS(C4:C18,">60") -> 10
A23: Average score of students who scored >60 in Math (AVERAGEIFS): | C23: =AVERAGEIFS(F4:F18,C4:C18,">60") -> 80.8
A24: Position of Student ID 'S105' in list (XMATCH): | C24: =_xlfn.XMATCH("S105",A4:A18) -> 5
A25: ↳ Same, using INDEX/MATCH-safe alternative (MATCH): | C25: =MATCH("S105",A4:A18,0) -> 5
A27: Students with Average above 80 (FILTER):
A28: =_xlfn._xlws.FILTER(B4:B18,F4:F18>80) -> Aarav Sharma

Sheet Lookup_Data
A1: Reference / Master Tables
A3: Product Master | E3: Salesperson Performance (Monthly Sales Amount)
A4: ProductCode | B4: ProductName | C4: Price | E4: Salesperson | F4: Jan | G4: Feb | H4: Mar | I4: Apr | J4: May | K4: Jun
A5: P001 | B5: Wireless Mouse | C5: 799 | E5: Rohit | F5: 45000 | G5: 52000 | H5: 61000 | I5: 47000 | J5: 58000 | K5: 63000
A6: P002 | B6: Mechanical Keyboard | C6: 2499 | E6: Neha | F6: 38000 | G6: 41000 | H6: 39000 | I6: 50000 | J6: 48000 | K6: 55000
A7: P003 | B7: 27-inch Monitor | C7: 12999 | E7: Aman | F7: 60000 | G7: 58000 | H7: 62000 | I7: 65000 | J7: 70000 | K7: 68000
A8: P004 | B8: USB-C Hub | C8: 1599 | E8: Priya | F8: 29000 | G8: 33000 | H8: 31000 | I8: 40000 | J8: 42000 | K8: 39000
A9: P005 | B9: Laptop Stand | C9: 999 | E9: Karan | F9: 52000 | G9: 49000 | H9: 55000 | I9: 53000 | J9: 60000 | K9: 57000
A10: P006 | B10: Webcam HD | C10: 1899
A11: P007 | B11: Noise Cancelling Headset | C11: 4499
A12: P008 | B12: External SSD 1TB | C12: 6999

Sheet Sales
A1: Sales Transactions | G1: Tax Rate: | H1: 0.18
A3: OrderID | B3: ProductCode | C3: Region | D3: Salesperson | E3: Qty | F3: Unit Price (VLOOKUP) | G3: Total | H3: Discount % | I3: Final Amount | J3: Total + Tax (Absolute Ref)
A4: O1001 | B4: P001 | C4: North | D4: Rohit | E4: 3 | F4: =VLOOKUP(B4,Lookup_Data!$A$5:$C$12,3,FALSE) -> 799 | G4: =E4*F4 -> 2397 | H4: =IF(OR(G4>10000,E4>10),0.1,0) -> 0 | I4: =G4*(1-H4) -> 2397 | J4: =G4*(1+$H$1) -> 2828.46
A5: O1002 | B5: P003 | C5: South | D5: Neha | E5: 1 | F5: =VLOOKUP(B5,Lookup_Data!$A$5:$C$12,3,FALSE) -> 12999 | G5: =E5*F5 -> 12999 | H5: =IF(OR(G5>10000,E5>10),0.1,0) -> 0.1 | I5: =G5*(1-H5) -> 11699.1 | J5: =G5*(1+$H$1) -> 15338.82
A6: O1003 | B6: P002 | C6: East | D6: Aman | E6: 5 | F6: =VLOOKUP(B6,Lookup_Data!$A$5:$C$12,3,FALSE) -> 2499 | G6: =E6*F6 -> 12495 | H6: =IF(OR(G6>10000,E6>10),0.1,0) -> 0.1 | I6: =G6*(1-H6) -> 11245.5 | J6: =G6*(1+$H$1) -> 14744.1
A7: O1004 | B7: P005 | C7: North | D7: Priya | E7: 12 | F7: =VLOOKUP(B7,Lookup_Data!$A$5:$C$12,3,FALSE) -> 999 | G7: =E7*F7 -> 11988 | H7: =IF(OR(G7>10000,E7>10),0.1,0) -> 0.1 | I7: =G7*(1-H7) -> 10789.2 | J7: =G7*(1+$H$1) -> 14145.84
A8: O1005 | B8: P007 | C8: West | D8: Karan | E8: 2 | F8: =VLOOKUP(B8,Lookup_Data!$A$5:$C$12,3,FALSE) -> 4499 | G8: =E8*F8 -> 8998 | H8: =IF(OR(G8>10000,E8>10),0.1,0) -> 0 | I8: =G8*(1-H8) -> 8998 | J8: =G8*(1+$H$1) -> 10617.64
A9: O1006 | B9: P004 | C9: South | D9: Rohit | E9: 8 | F9: =VLOOKUP(B9,Lookup_Data!$A$5:$C$12,3,FALSE) -> 1599 | G9: =E9*F9 -> 12792 | H9: =IF(OR(G9>10000,E9>10),0.1,0) -> 0.1 | I9: =G9*(1-H9) -> 11512.8 | J9: =G9*(1+$H$1) -> 15094.56
A10: O1007 | B10: P006 | C10: East | D10: Neha | E10: 4 | F10: =VLOOKUP(B10,Lookup_Data!$A$5:$C$12,3,FALSE) -> 1899 | G10: =E10*F10 -> 7596 | H10: =IF(OR(G10>10000,E10>10),0.1,0) -> 0 | I10: =G10*(1-H10) -> 7596 | J10: =G10*(1+$H$1) -> 8963.28
A11: O1008 | B11: P008 | C11: West | D11: Aman | E11: 1 | F11: =VLOOKUP(B11,Lookup_Data!$A$5:$C$12,3,FALSE) -> 6999 | G11: =E11*F11 -> 6999 | H11: =IF(OR(G11>10000,E11>10),0.1,0) -> 0 | I11: =G11*(1-H11) -> 6999 | J11: =G11*(1+$H$1) -> 8258.82
A12: O1009 | B12: P001 | C12: North | D12: Karan | E12: 15 | F12: =VLOOKUP(B12,Lookup_Data!$A$5:$C$12,3,FALSE) -> 799 | G12: =E12*F12 -> 11985 | H12: =IF(OR(G12>10000,E12>10),0.1,0) -> 0.1 | I12: =G12*(1-H12) -> 10786.5 | J12: =G12*(1+$H$1) -> 14142.3
A13: O1010 | B13: P003 | C13: East | D13: Priya | E13: 2 | F13: =VLOOKUP(B13,Lookup_Data!$A$5:$C$12,3,FALSE) -> 12999 | G13: =E13*F13 -> 25998 | H13: =IF(OR(G13>10000,E13>10),0.1,0) -> 0.1 | I13: =G13*(1-H13) -> 23398.2 | J13: =G13*(1+$H$1) -> 30677.64
A16: Analysis / Formula Demos
A17: Total sales — Region 'North', Product 'P001' (SUMIFS): | C17: =SUMIFS(G4:G13,C4:C13,"North",B4:B13,"P001") -> 14382
A18: Sales value for 'Aman' in 'Mar' (INDEX/MATCH): | C18: =INDEX(Lookup_Data!$F$5:$K$9,MATCH("Aman",Lookup_Data!$E$5:$E$9,0),MATCH("Mar",Lookup_Data!$F$4:$K$4,0)) -> 62000
A19: Same, using XLOOKUP (flexible search — Excel 365): | C19: =_xlfn.XLOOKUP("Mar",Lookup_Data!$F$4:$K$4,INDEX(Lookup_Data!$F$5:$K$9,MATCH("Aman",Lookup_Data!$E$5:$E$9,0),0)) -> 62000
A20: Position of ProductCode 'P005' in Product Master list (XMATCH): | C20: =_xlfn.XMATCH("P005",Lookup_Data!$A$5:$A$12) -> 5
A21: ↳ Safe alternative (MATCH): | C21: =MATCH("P005",Lookup_Data!$A$5:$A$12,0) -> 5
A22: Dynamic 3-month rolling sum for 'Rohit' from Feb (OFFSET): | C22: =SUM(OFFSET(Lookup_Data!$E$5,0,1,1,3)) -> 158000 | E22: ↑ OFFSET(start_cell, rows, cols, height, width)
A23: Dynamic reference — build range name from text (INDIRECT): | C23: =SUM(INDIRECT("Lookup_Data!F6:F10")) -> 179000 | E23: ↑ Change the text inside INDIRECT to point anywhere, e.g. "Lookup_Data!G6:G10"

Sheet Employees
A1: Employee Records
A3: EmpID | B3: Name | C3: Department | D3: Date of Birth | E3: Date of Joining | F3: Salary | G3: Age (Years) | H3: Days Since Joining | I3: Bonus (10%) | J3: Bonus Rounded | K3: Bonus Ceiling(100) | L3: Bonus Floor(100)
A4: E201 | B4: Rohit Sinha | C4: Sales | D4: 33677 | E4: 43252 | F4: 58000 | G4: =DATEDIF(D4,TODAY(),"y") -> 34 | H4: =TODAY()-E4 -> 3013 | I4: =F4*0.1 -> 5800 | J4: =ROUND(I4,0) -> 5800 | K4: =CEILING(I4,100) -> 5800 | L4: =FLOOR(I4,100) -> 5800
A5: E202 | B5: Neha Kulkarni | C5: Sales | D5: 34902 | E5: 43845 | F5: 52000 | G5: =DATEDIF(D5,TODAY(),"y") -> 31 | H5: =TODAY()-E5 -> 2420 | I5: =F5*0.1 -> 5200 | J5: =ROUND(I5,0) -> 5200 | K5: =CEILING(I5,100) -> 5200 | L5: =FLOOR(I5,100) -> 5200
A6: E203 | B6: Aman Chopra | C6: Sales | D6: 32452 | E6: 42073 | F6: 71000 | G6: =DATEDIF(D6,TODAY(),"y") -> 37 | H6: =TODAY()-E6 -> 4192 | I6: =F6*0.1 -> 7100 | J6: =ROUND(I6,0) -> 7100 | K6: =CEILING(I6,100) -> 7100 | L6: =FLOOR(I6,100) -> 7100
A7: E204 | B7: Priya Menon | C7: Sales | D7: 35460 | E7: 44431 | F7: 49000 | G7: =DATEDIF(D7,TODAY(),"y") -> 29 | H7: =TODAY()-E7 -> 1834 | I7: =F7*0.1 -> 4900 | J7: =ROUND(I7,0) -> 4900 | K7: =CEILING(I7,100) -> 4900 | L7: =FLOOR(I7,100) -> 4900
A8: E205 | B8: Karan Dutta | C8: Sales | D8: 33134 | E8: 43046 | F8: 64000 | G8: =DATEDIF(D8,TODAY(),"y") -> 35 | H8: =TODAY()-E8 -> 3219 | I8: =F8*0.1 -> 6400 | J8: =ROUND(I8,0) -> 6400 | K8: =CEILING(I8,100) -> 6400 | L8: =FLOOR(I8,100) -> 6400
A9: E206 | B9: Sneha Pillai | C9: Marketing | D9: 34456 | E9: 44606 | F9: 46000 | G9: =DATEDIF(D9,TODAY(),"y") -> 32 | H9: =TODAY()-E9 -> 1659 | I9: =F9*0.1 -> 4600 | J9: =ROUND(I9,0) -> 4600 | K9: =CEILING(I9,100) -> 4600 | L9: =FLOOR(I9,100) -> 4600
A10: E207 | B10: Rahul Bhatt | C10: Finance | D10: 31392 | E10: 41456 | F10: 88000 | G10: =DATEDIF(D10,TODAY(),"y") -> 40 | H10: =TODAY()-E10 -> 4809 | I10: =F10*0.1 -> 8800 | J10: =ROUND(I10,0) -> 8800 | K10: =CEILING(I10,100) -> 8800 | L10: =FLOOR(I10,100) -> 8800
A11: E208 | B11: Tanvi Shah | C11: HR | D11: 35894 | E11: 45174 | F11: 42000 | G11: =DATEDIF(D11,TODAY(),"y") -> 28 | H11: =TODAY()-E11 -> 1091 | I11: =F11*0.1 -> 4200 | J11: =ROUND(I11,0) -> 4200 | K11: =CEILING(I11,100) -> 4200 | L11: =FLOOR(I11,100) -> 4200
A14: Search Tool — XLOOKUP Demo
A15: Enter EmpID here: | B15: E203
A16: Salary (XLOOKUP): | B16: =_xlfn.XLOOKUP(B15,A4:A11,F4:F11) -> 71000
A17: ↳ Safe alternative (INDEX/MATCH): | B17: =INDEX(F4:F11,MATCH(B15,A4:A11,0)) -> 71000
